game/__init__.py
game/main.py
game/mechanics.py
game/model.py
game/window.py
PJWSTK_Tetris_game-0.9.96.dist-info/LICENSE.txt
PJWSTK_Tetris_game-0.9.96.dist-info/METADATA
PJWSTK_Tetris_game-0.9.96.dist-info/WHEEL
PJWSTK_Tetris_game-0.9.96.dist-info/entry_points.txt
PJWSTK_Tetris_game-0.9.96.dist-info/top_level.txt
PJWSTK_Tetris_game-0.9.96.dist-info/RECORD
