Metadata-Version: 2.1
Name: PJWSTK-Tetris-game
Version: 0.9.96
Summary: Tetris game
Home-page: https://github.com/tomaszlemke/Tetris1.0
Author: Tomasz Lemke & Krzysztof Skwira
Author-email: s19471@pjwstk.edu.pl
License: MIT
Platform: UNKNOWN
Classifier: Programming Language :: Python :: 3
Classifier: License :: OSI Approved :: MIT License
Classifier: Operating System :: OS Independent
Classifier: Topic :: Software Development :: Libraries :: pygame
Classifier: Development Status :: 3 - Alpha
Classifier: Topic :: Games/Entertainment :: Puzzle Games
Requires-Dist: pygame (~=1.9)
